setup.py
composition_utils/__init__.py
composition_utils.egg-info/PKG-INFO
composition_utils.egg-info/SOURCES.txt
composition_utils.egg-info/dependency_links.txt
composition_utils.egg-info/requires.txt
composition_utils.egg-info/top_level.txt
composition_utils/driver/__init__.py
composition_utils/driver/benchmarking.py
composition_utils/driver/driver.py
composition_utils/model/__init__.py
composition_utils/model/model.py