Metadata-Version: 1.0
Name: composition-utils
Version: 1.2
Summary: utilities for benchmarking models used in Clipper model composition research
Home-page: http://clipper.ai
Author: Corey Zumar
Author-email: czumar@berkeley.edu
License: UNKNOWN
Platform: UNKNOWN
